bulksms/__init__.py
bulksms/api.py
bulksms/test_api.py
bulksms/utils.py
bulksms-1.1.1.dist-info/LICENSE.rst
bulksms-1.1.1.dist-info/METADATA
bulksms-1.1.1.dist-info/WHEEL
bulksms-1.1.1.dist-info/top_level.txt
bulksms-1.1.1.dist-info/RECORD
