Metadata-Version: 2.1
Name: bulksms
Version: 1.1.1
Summary: The simplest way to text people (send SMS) via python.
Author-email: Michele Mazzucchi <support@tattler.dev>
Project-URL: Repository, https://github.com/tattler-community/bulksms
Project-URL: Issues, https://github.com/tattler-community/bulksms/issues
Classifier: License :: OSI Approved :: BSD License
Classifier: Intended Audience :: Developers
Classifier: Programming Language :: Python :: 3 :: Only
Classifier: Operating System :: POSIX
Classifier: Development Status :: 5 - Production/Stable
Classifier: Environment :: Console
Classifier: Topic :: Communications
Requires-Python: >=3.9
License-File: LICENSE.rst
